postfiat/models/__init__.py
postfiat/models/transaction.py
postfiat/nodes/task/__init__.py
postfiat/nodes/task/constants.py
postfiat/nodes/task/codecs/v0/__init__.py
postfiat/nodes/task/codecs/v0/errors.py
postfiat/nodes/task/codecs/v0/common/__init__.py
postfiat/nodes/task/codecs/v0/common/encode.py
postfiat/nodes/task/codecs/v0/remembrancer/__init__.py
postfiat/nodes/task/codecs/v0/remembrancer/decode.py
postfiat/nodes/task/codecs/v0/remembrancer/encode.py
postfiat/nodes/task/codecs/v0/serialization/__init__.py
postfiat/nodes/task/codecs/v0/serialization/chunking.py
postfiat/nodes/task/codecs/v0/serialization/cipher.py
postfiat/nodes/task/codecs/v0/serialization/compression.py
postfiat/nodes/task/codecs/v0/task/__init__.py
postfiat/nodes/task/codecs/v0/task/decode.py
postfiat/nodes/task/codecs/v0/task/encode.py
postfiat/nodes/task/codecs/v0/task/labels.py
postfiat/nodes/task/models/messages/__init__.py
postfiat/nodes/task/models/messages/base.py
postfiat/nodes/task/models/messages/types.py
postfiat/nodes/task/state/__init__.py
postfiat/rpc/__init__.py
postfiat/rpc/cache.py
postfiat/rpc/errors.py
postfiat/rpc/network.py
postfiat/rpc/protocol.py
postfiat/rpc/sender.py
postfiat/utils/streams/__init__.py
postfiat_sdk-0.1.1.dist-info/METADATA
postfiat_sdk-0.1.1.dist-info/WHEEL
postfiat_sdk-0.1.1.dist-info/licenses/LICENSE
postfiat_sdk-0.1.1.dist-info/RECORD
