Metadata-Version: 2.3
Name: postfiat-sdk
Version: 0.1.1
Summary: SDK for the Post Fiat Network
License: MPL-2.0
Requires-Python: >=3.12
Requires-Dist: aiofiles~=24.1.0
Requires-Dist: brotli~=1.1.0
Requires-Dist: cryptography~=44.0.0
Requires-Dist: pydantic~=2.10.6
Requires-Dist: pynacl~=1.5.0
Requires-Dist: xrpl-py~=4.0.0
Provides-Extra: dev
Requires-Dist: hatch~=1.14.0; extra == 'dev'
Requires-Dist: pytest-asyncio~=0.25.3; extra == 'dev'
Requires-Dist: pytest~=8.3.4; extra == 'dev'
